Hapi/__init__.py
Hapi/catchment.py
Hapi/hapi_warnings.py
Hapi/run.py
Hapi/hm/__init__.py
Hapi/hm/calibration.py
Hapi/hm/crosssection.py
Hapi/hm/event.py
Hapi/hm/inputs.py
Hapi/hm/interface.py
Hapi/hm/river.py
Hapi/hm/saintvenant.py
Hapi/plot/__init__.py
Hapi/plot/visualizer.py
Hapi/rrm/__init__.py
Hapi/rrm/calibration.py
Hapi/rrm/distparameters.py
Hapi/rrm/distrrm.py
Hapi/rrm/hbv.py
Hapi/rrm/hbv_bergestrom92.py
Hapi/rrm/hbv_lake.py
Hapi/rrm/hbvlumped.py
Hapi/rrm/hbvold.py
Hapi/rrm/inputs.py
Hapi/rrm/routing.py
Hapi/rrm/wrapper.py
HAPI_Nile-1.6.0.dist-info/AUTHORS.rst
HAPI_Nile-1.6.0.dist-info/LICENSE.md
HAPI_Nile-1.6.0.dist-info/METADATA
HAPI_Nile-1.6.0.dist-info/WHEEL
HAPI_Nile-1.6.0.dist-info/top_level.txt
HAPI_Nile-1.6.0.dist-info/RECORD
