Metadata-Version: 2.1
Name: HAPI-Nile
Version: 1.6.0
Summary: Distributed hydrological-model
Home-page: https://github.com/MAfarrag/Hapi
Author: Mostafa Farrag
Author-email: moah.farag@gmail.come
License: GNU General Public License v3
Keywords: Hydrology,Distributed hydrological model,Hydaulic model
Classifier: Development Status :: 5 - Production/Stable
Classifier: Environment :: Console
Classifier: License :: OSI Approved :: GNU General Public License v3 (GPLv3)
Classifier: Natural Language :: English
Classifier: Programming Language :: Python :: 3
Classifier: Programming Language :: Python :: 3.9
Classifier: Programming Language :: Python :: 3.10
Classifier: Programming Language :: Python :: 3.11
Classifier: Topic :: Scientific/Engineering :: Hydrology
Classifier: Topic :: Scientific/Engineering :: GIS
Classifier: Intended Audience :: Science/Research
Classifier: Intended Audience :: Developers
License-File: LICENSE.md
License-File: AUTHORS.rst
Requires-Dist: cleopatra (>=0.2.7)
Requires-Dist: digitalearth (>=0.1.11)
Requires-Dist: earth2observe (>=0.2.2)
Requires-Dist: Fiona (>=1.8.21)
Requires-Dist: gdal (>=3.5.3)
Requires-Dist: geopandas (>=0.12.2)
Requires-Dist: geostatista (>=0.1.6)
Requires-Dist: joblib (>=1.2.0)
Requires-Dist: loguru (>=0.6.0)
Requires-Dist: matplotlib (>=3.6.3)
Requires-Dist: numpy (>=1.24.1)
Requires-Dist: Oasis-Optimization (>=1.0.2)
Requires-Dist: pandas (>=1.4.4)
Requires-Dist: pathlib (>=1.0.1)
Requires-Dist: pip (>=22.3.1)
Requires-Dist: pyramids-gis (>=0.3.2)
Requires-Dist: PyYAML (>=0.6.0)
Requires-Dist: rasterio (>=1.3.2)
Requires-Dist: rasterstats (>=0.17.0)
Requires-Dist: requests (>=2.28.1)
Requires-Dist: scipy (>=1.9.1)
Requires-Dist: serapeum-utils (>=0.1.1)
Requires-Dist: statista (>=0.1.8)
Requires-Dist: statsmodels (>=0.13.2)
